castor/__init__.py
castor/attributed_str.py
castor/cli.py
castor/jsoner.py
castor/print_utils.py
castor/table.py
castor/text.py
castor/tree.py
gxCastor-0.2.5.data/scripts/castor
gxCastor-0.2.5.dist-info/LICENSE
gxCastor-0.2.5.dist-info/METADATA
gxCastor-0.2.5.dist-info/WHEEL
gxCastor-0.2.5.dist-info/top_level.txt
gxCastor-0.2.5.dist-info/RECORD
