Metadata-Version: 2.1
Name: gxCastor
Version: 0.2.5
Summary: Simple file analyzer
Home-page: UNKNOWN
Author: gawainx
Author-email: liangyi@bupt.edu.cn
License: UNKNOWN
Platform: UNKNOWN
Classifier: Programming Language :: Python :: 3.8
Classifier: License :: OSI Approved :: GNU General Public License v3 (GPLv3)
Classifier: Operating System :: OS Independent
Requires-Dist: typer
Requires-Dist: rich
Requires-Dist: pptree
Requires-Dist: toml
